decoRouter/__init__.py
decoRouter/decoRouter.py
starlette_decoRouter-1.0.0.dist-info/METADATA
starlette_decoRouter-1.0.0.dist-info/WHEEL
starlette_decoRouter-1.0.0.dist-info/top_level.txt
starlette_decoRouter-1.0.0.dist-info/RECORD
