Metadata-Version: 2.1
Name: starlette-decoRouter
Version: 1.0.0
Summary: FastAPI style decorators for starlette ASGI
Home-page: https://github.com/MrPigss/DecoRouter
Author: Thomas Eeckhout
Author-email: Thomas.Eeckhout@outlook.be
License: UNKNOWN
Keywords: ASGI,routing,starlette,fastapi
Platform: UNKNOWN
Classifier: Intended Audience :: Developers
Classifier: Framework :: FastAPI
Classifier: Programming Language :: Python :: 3.8
Classifier: Programming Language :: Python :: 3.9
Classifier: Programming Language :: Python :: 3.10
Classifier: Programming Language :: Python :: 3 :: Only
Requires-Python: >=3.8, <4
Requires-Dist: starlette
